{
  "meta": {
    "descripcion": "Citas médicas de ejemplo - Duración fija 30min",
    "fecha_generacion": "2025-01-15",
    "duracion_estandar_minutos": 30,
    "total_citas": 3
  },
  "citas": [
    {
      "id_cita": "CITA-EX-001",
      "id_medico": "MED-EX-001",
      "paciente": {
        "iniciales": "P.G.",
        "id_anonimo": "PAC-EX-001"
      },
      "fecha": "2025-02-20",
      "hora": "09:30",
      "estado": "confirmada",
      "motivo": "Control anual"
    },
    {
      "id_cita": "CITA-EX-002",
      "id_medico": "MED-EX-002",
      "paciente": {
        "iniciales": "M.R.",
        "id_anonimo": "PAC-EX-002"
      },
      "fecha": "2025-02-21",
      "hora": "15:00",
      "estado": "pendiente",
      "motivo": "Dolor de espalda"
    }
  ]
}
